mstarpy/__init__.py
mstarpy/error.py
mstarpy/funds.py
mstarpy/search.py
mstarpy/security.py
mstarpy/stock.py
mstarpy/utils.py
mstarpy-8.0.3.dist-info/METADATA
mstarpy-8.0.3.dist-info/WHEEL
mstarpy-8.0.3.dist-info/top_level.txt
mstarpy-8.0.3.dist-info/RECORD
