Metadata-Version: 2.4
Name: mstarpy
Version: 8.0.3
Summary: Mutual funds and stocks data extraction from MorningStar with Python
Author: Maël Jourdain
Author-email: mael.jourdain@gmail.com
License: MIT License
Requires-Python: >=3.10
Requires-Dist: pandas>=1.3.5
Requires-Dist: requests>=2.28.1
Requires-Dist: statsmodels>=0.14.5
Requires-Dist: matplotlib>=3.10.5
Dynamic: author
Dynamic: author-email
Dynamic: description
Dynamic: description-content-type
Dynamic: license
Dynamic: requires-dist
Dynamic: requires-python
Dynamic: summary
